kishw/__init__.py
kishw/_version.py
kishw/handlers.py
kishw/jlfe.py
kishw/widgets.py
kishw/tests/__init__.py
kishw/tests/test_handlers.py
kishw-1.0.0.data/data/etc/jupyter/jupyter_notebook_config.d/kishw.json
kishw-1.0.0.data/data/etc/jupyter/jupyter_server_config.d/kishw.json
kishw-1.0.0.data/data/share/jupyter/labextensions/kishw/build_log.json
kishw-1.0.0.data/data/share/jupyter/labextensions/kishw/install.json
kishw-1.0.0.data/data/share/jupyter/labextensions/kishw/package.json
kishw-1.0.0.data/data/share/jupyter/labextensions/kishw/static/lib_index_js.fa40c279d71832aa8383.js
kishw-1.0.0.data/data/share/jupyter/labextensions/kishw/static/lib_index_js.fa40c279d71832aa8383.js.map
kishw-1.0.0.data/data/share/jupyter/labextensions/kishw/static/lib_plugin_js.219cc9c488d8e3fdb7fa.js
kishw-1.0.0.data/data/share/jupyter/labextensions/kishw/static/lib_plugin_js.219cc9c488d8e3fdb7fa.js.map
kishw-1.0.0.data/data/share/jupyter/labextensions/kishw/static/lib_widget_js.b8a3cc44f6f44f8d7234.js
kishw-1.0.0.data/data/share/jupyter/labextensions/kishw/static/lib_widget_js.b8a3cc44f6f44f8d7234.js.map
kishw-1.0.0.data/data/share/jupyter/labextensions/kishw/static/remoteEntry.f298dfbade21bf5ff9ab.js
kishw-1.0.0.data/data/share/jupyter/labextensions/kishw/static/remoteEntry.f298dfbade21bf5ff9ab.js.map
kishw-1.0.0.data/data/share/jupyter/labextensions/kishw/static/style.js
kishw-1.0.0.data/data/share/jupyter/labextensions/kishw/static/style_index_js.4a5e3de1295d1ae1a866.js
kishw-1.0.0.data/data/share/jupyter/labextensions/kishw/static/style_index_js.4a5e3de1295d1ae1a866.js.map
kishw-1.0.0.data/data/share/jupyter/labextensions/kishw/static/vendors-node_modules_css-loader_dist_runtime_api_js-node_modules_css-loader_dist_runtime_cssW-72eba1.52b5925629bf8c4b1748.js
kishw-1.0.0.data/data/share/jupyter/labextensions/kishw/static/vendors-node_modules_css-loader_dist_runtime_api_js-node_modules_css-loader_dist_runtime_cssW-72eba1.52b5925629bf8c4b1748.js.map
kishw-1.0.0.dist-info/METADATA
kishw-1.0.0.dist-info/WHEEL
kishw-1.0.0.dist-info/licenses/LICENSE
kishw-1.0.0.dist-info/RECORD
